blizzardapi2/__init__.py
blizzardapi2/api.py
blizzardapi2/blizzard_api.py
blizzardapi2/types.py
blizzardapi2/battlenet/__init__.py
blizzardapi2/battlenet/battlenet_api.py
blizzardapi2/battlenet/battlenet_oauth_api.py
blizzardapi2/diablo3/__init__.py
blizzardapi2/diablo3/diablo3_api.py
blizzardapi2/diablo3/diablo3_community_api.py
blizzardapi2/diablo3/diablo3_game_data_api.py
blizzardapi2/hearthstone/__init__.py
blizzardapi2/hearthstone/hearthstone_api.py
blizzardapi2/hearthstone/hearthstone_game_data_api.py
blizzardapi2/starcraft2/__init__.py
blizzardapi2/starcraft2/starcraft2_api.py
blizzardapi2/starcraft2/starcraft2_community_api.py
blizzardapi2/starcraft2/starcraft2_game_data_api.py
blizzardapi2/wow/__init__.py
blizzardapi2/wow/wow_api.py
blizzardapi2/wow/wow_game_data_api.py
blizzardapi2/wow/wow_profile_api.py
blizzardapi2-2.1.17.dist-info/licenses/LICENSE
blizzardapi2-2.1.17.dist-info/METADATA
blizzardapi2-2.1.17.dist-info/WHEEL
blizzardapi2-2.1.17.dist-info/top_level.txt
blizzardapi2-2.1.17.dist-info/RECORD
