Metadata-Version: 2.4
Name: blizzardapi2
Version: 2.1.17
Summary: A Python wrapper for Blizzard API
Author-email: lostcol0ny <c098os0k@4wrd.cc>
License-Expression: MIT
Classifier: Programming Language :: Python :: 3
Classifier: Programming Language :: Python :: 3.11
Classifier: Programming Language :: Python :: 3.12
Classifier: Programming Language :: Python :: 3.13
Classifier: Operating System :: OS Independent
Requires-Python: >=3.11
License-File: LICENSE
Requires-Dist: requests<3.0.0,>=2.32.3
Requires-Dist: black<26.0.0,>=24.4.2
Requires-Dist: pytest<10.0.0,>=8.2.2
Requires-Dist: pytest-mock<4.0.0,>=3.14.0
Requires-Dist: ruff<1.0.0,>=0.3.0
Requires-Dist: pydantic>=2.11.6
Requires-Dist: aiohttp>=3.12.12
Provides-Extra: dev
Requires-Dist: pytest<10.0.0,>=8.2.2; extra == "dev"
Requires-Dist: pytest-mock<4.0.0,>=3.14.0; extra == "dev"
Requires-Dist: pytest-asyncio<2.0.0,>=0.23.5; extra == "dev"
Requires-Dist: black<26.0.0,>=24.4.2; extra == "dev"
Requires-Dist: ruff<1.0.0,>=0.3.0; extra == "dev"
Dynamic: license-file
